{
	"smelting": {
		"label": "Smelting",
		"type": "Recipe",
		"group": [
			"Latin Ligatures", "",
			"Latin Digraphs", "",
			"Latin", "",
			"Latino-Hellenic", "",
			"Latin Accented", "",
			"Latin Numerals", "",
			"Hellenic Ligatures", "",
			"Hellenic", "",
			"Hellenic Accented", "",
			"Hellenic Diacritics", "",
			"Cyrillic Ligatures", "",
			"Cyrillic Digraphs", "",
			"Cyrillic", "",
			"Cyrillic Accented", "",
			"Germanic Runic Elder Futhark",
			"Germanic Runic Futhork",
			"Germanic Runic Younger Futhark",
			"Germanic Runic Almanac",
			"Germanic Runic Later Younger Futhark",
			"Germanic Runic Medieval",
			"Cirth Runic", "",
			"Glagolitic", "",
			"Old Persian", "",
			"Manichaean", "",
			"Shavian Ligatures", "",
			"<cat>Diacritic Mark", "",
			"Smelting Special", "",
			"Extra Symbolistics", "",
			"Liturgy", "",
			"Pharmaceutical", "",
			"Alchemical", "",
			"Astrological", "",
			"Astronomical", "",
			"Occultic", "",
			"Geomantic", "",
			"Taoist", "",
			"Yijing", "",
			"Taixuanjing", "",
			"Chess", "",
			"Card", "",
			"Playing Card", "",
			"Wallet Signs", "",
			"Other Signs", "",
			"Other Symbols", "",
			"Miscellaneous Technical"
		],
		"groupKey": {}
	},
	"fastkeys": [{
		"label": "Fast Keys",
		"type": "Fast Key",
		"group": [
			"FK Diacritics Primary", "",
			"Special Fast Primary", "",
			"Spaces Primary", "",
			"Special Fast Left",
			"Wallet Signs Primary", "",
			"Spaces Left Alt", "",
			"Latin Primary", "",
			"Latin Accented Primary", "",
			"Cyrillic Primary", "",
			"Cyrillic Accented Primary", "",
			"Special Fast Secondary",
			"Spaces Secondary", "",
			"Wallet Signs Secondary", "",
			"Asian Quotes", "",
			"Other Signs", "",
			"Format Characters", "",
			"Misc", "",
			"Latin Ligatures", "",
			"Latin Secondary", "",
			"Latino-Hellenic Secondary", "",
			"Latin Accented Secondary", "",
			"Cyrillic Ligatures Secondary", "",
			"Cyrillic Digraphs Secondary", "",
			"Cyrillic Secondary", "",
			"Cyrillic Accented Secondary", "",
			"Yijing Secondary", "",
			"Special Right Shift",
			"Wallet Signs Right Shift", "",
			"Spaces Right Shift", "",
			"Latin Accented Tertiary", "",
			"Cyrillic Tertiary", "",
			"Special Fast RShift", "",
			"Wallet Signs Left Shift", "",
			"Spaces Left Shift", ""
		],
		"groupKey": {
			"FK Diacritics Primary": "<% LeftControl %/> <% LeftAlt %/>",
			"Special Fast Left": "<% LeftAlt %/>",
			"Special Fast Secondary": "<% RightAlt %/>",
			"Special Right Shift": "<% RightShift %/>",
			"Wallet Signs Left Shift": "<% LeftShift %/>"
		}
	}, {
		"label": "Fast Keys",
		"type": "Special Combinations",
		"group": ["Special Combinations"],
		"groupKey": {"Special Combinations": "@dictionary.combination_special"}
	}],
	"secondkeys": {
		"label": "Second Keys",
		"type": "Fast Key",
		"group": [
			"SK Diacritics Primary", "",
			"SK Spaces Primary", "",
			"SK Special Secondary", "",
			"SK Spaces Secondary", "",
			"SK Special Left Alt", "",
			"SK Spaces Left Alt", ""
		],
		"groupKey": {
			"SK Diacritics Primary": "<% LeftControl %/> <% LeftAlt %/>",
			"SK Special Secondary": "<% RightAlt %/>",
			"SK Special Left Alt": "<% LeftAlt %/>"
		}
	},
	"tertiarykeys": {
		"label": "Tertiary Keys",
		"type": "Fast Key",
		"group": [
			"TK Diacritics Primary", ""
		],
		"groupKey": {
			"TK Diacritics Primary": "<% LeftControl %/> <% LeftAlt %/>"
		}
	},
	"scripts": {
		"label": "Scripts",
		"type": "Alternative Layout",
		"group": [
			"Mathematical", "",
			"Math", "",
			"Math Spaces", "",
			"Hellenic", "",
			"Hellenic Accented", "",
			"Hellenic Diacritics", "",
			"Hellenic Punctuation",
			"Hellenic Specials", "",
			"Germanic Runic Elder Futhark", "",
			"Germanic Runic Futhork", "",
			"Germanic Runic Younger Futhark", "",
			"Germanic Runic Almanac", "",
			"Germanic Runic Later Younger Futhark", "",
			"Germanic Runic Medieval", "",
			"Germanic Runic", "",
			"Cirth Runic",
			"Tolkien Runic", "",
			"Runic Punctuation", "",
			"Glagolitic",
			"Cyrillic Diacritics", "",
			"Old Turkic",
			"Old Turkic Orkhon", "",
			"Old Turkic Yenisei", "",
			"Old Permic", "",
			"Old Hungarian", "Old Hungarian Numerals", "",
			"Gothic", "Gothic Numerals", "",
			"Caucasian Albanian", "",
			"Old Italic", "Old Italic Numerals", "",
			"Phoenician", "Phoenician Numerals", "",
			"Samaritan", "",
			"South Arabian", "South Arabian Numerals", "",
			"North Arabian", "North Arabian Numerals", "",
			"Carian", "",
			"Lycian", "",
			"Lydian", "",
			"Sidetic", "",
			"Cypriot Syllabary", "",
			"Tifinagh", "",
			"Ugaritic", "",
			"Old Persian", "Old Persian Numerals", "",
			"Imperial Aramaic", "Imperial Aramaic Numerals", "",
			"Palmyrene", "Palmyrene Numerals", "",
			"Parthian", "Parthian Numerals", "",
			"Manichaean", "Manichaean Numerals", "",
			"Deseret", "",
			"Shavian", "Shavian Ligatures", ""
		],
		"groupKey": {
			"Mathematical": "@script_labels.math",
			"Hellenic": "@script_labels.hellenic",
			"Germanic Runic Elder Futhark": "@script_labels.futhark",
			"Germanic Runic Futhork": "@script_labels.futhork",
			"Germanic Runic Younger Futhark": "@script_labels.futhark_younger",
			"Germanic Runic Almanac": "@script_labels.futhark_almanac",
			"Germanic Runic Later Younger Futhark": "@script_labels.futhark_younger_later",
			"Germanic Runic Medieval": "@script_labels.medieval_runes",
			"Runic Punctuation": "@script_labels.runic_punctuation",
			"Glagolitic": "@script_labels.glagolitic",
			"Old Turkic": "@script_labels.old_turkic",
			"Old Turkic Orkhon": "@script_labels.old_turkic.orkhon",
			"Old Turkic Yenisei": "@script_labels.old_turkic.yenisei",
			"Old Permic": "@script_labels.old_permic",
			"Old Hungarian": "@script_labels.old_hungarian",
			"Gothic": "@script_labels.gothic",
			"Caucasian Albanian": "@script_labels.caucasian_albanian",
			"Old Italic": "@script_labels.old_italic",
			"Phoenician": "@script_labels.phoenician",
			"Samaritan": "@script_labels.samaritan",
			"South Arabian": "@script_labels.ancient_south_arabian",
			"North Arabian": "@script_labels.ancient_north_arabian",
			"Carian": "@script_labels.carian",
			"Lycian": "@script_labels.lycian",
			"Lydian": "@script_labels.lydian",
			"Sidetic": "@script_labels.sidetic",
			"Cypriot Syllabary": "@script_labels.cypriot_syllabary",
			"Tifinagh": "@script_labels.tifinagh",
			"Ugaritic": "@script_labels.ugaritic",
			"Old Persian": "@script_labels.old_persian",
			"Imperial Aramaic": "@script_labels.imperial_aramaic",
			"Palmyrene": "@script_labels.palmyrene",
			"Parthian": "@script_labels.parthian",
			"Manichaean": "@script_labels.manichaean",
			"Deseret": "@script_labels.deseret.short",
			"Shavian": "@script_labels.shavian.short"
		}
	},
	"ipa_keys": {
		"label": "Scripts",
		"type": "Alternative Layout",
		"group": [
			"IPA Commands", "",
			"IPA"
		],
		"groupKey": {
			"IPA Commands": "@dictionary.commands",
			"IPA": "@script_labels.ipa.short"
		}
	},
	"ipa_recipes": {
		"label": "Scripts",
		"type": "Recipe",
		"useLayoutTitles": true,
		"group": [
			"IPA"
		],
		"groupKey": {
			"IPA": "@script_labels.ipa.short"
		}
	},
	"TELEXVNI": {
		"label": "TELEX/VNI",
		"type": "TELEX/VNI",
		"group": [
			"TELEX/VNI Vietnamese", "",
			"TELEX/VNI Jorai", "",
			"TELEX/VNI Chinese Romanization", ""
		],
		"groupKey": {
			"TELEX/VNI Vietnamese": "@telex_script_processor.labels.vietnamese",
			"TELEX/VNI Jorai": "@telex_script_processor.labels.jorai",
			"TELEX/VNI Chinese Romanization": "@telex_script_processor.labels.chinese_romanization"
		},
		"subType": {
			"TELEX/VNI Vietnamese": "vietnamese",
			"TELEX/VNI Jorai": "jorai",
			"TELEX/VNI Chinese Romanization": "chinese_romanization"
		},
		"combinationKey": {
			"TELEX/VNI Vietnamese": "<% RightAlt %/> F2",
			"TELEX/VNI Jorai": "<% RightAlt %/> F2",
			"TELEX/VNI Chinese Romanization": "<% RightAlt %/> <% RightShift %/> F2"
		}
	},
	"all": {
		"label": "All",
		"type": "",
		"group": ["i)^(?!Custom)"]
	},
	"favorites": {
		"label": "Favorites",
		"type": "",
		"group": ["Favorites"]
	}
}